<SerialDevice name="IRS300_20">
    <Frame name="Robot_Base" type="Movable">
        <RPY> 0 0 0 </RPY> <Pos> 0 0 0</Pos> 
        <Property name="ObjType"  desc="Object Type"> OBJ_TYPE_ROBOT </Property>
		<Property name="PostProcess" desc=" lua">Inovance.lua</Property>
		<Property name="DeviceId" desc="The id to distinguish this device to others"> IRS300_20_170TS5 </Property>
    </Frame>


    <DHJoint name="Joint1" alpha="0" a="0" d="500" offset="0" type="craig"></DHJoint>

    <DHJoint name="Joint2" alpha="90" a="170" d="0" offset="90" type="craig"></DHJoint>

    <DHJoint name="Joint3" alpha="0" a="780" d="0" offset="0" type="craig"></DHJoint>

    <DHJoint name="Joint4" alpha="90" a="140" d="760" offset="0" type="craig"></DHJoint>

    <DHJoint name="Joint5"  alpha="-90" a="0" d="0" offset="0" type="craig"></DHJoint>

    <DHJoint name="Joint6" alpha="90" a="0" d="0" offset="0" type="craig"></DHJoint>

    <Frame name="ToolMount" refframe="Joint6" >
        <RPY> 0 0 0 </RPY> <Pos> 0 0 123 </Pos> 
    </Frame>

    <PosLimit refjoint="Joint1" min="-170" max="170" />   <!--Êý¾Ý²Î¿¼robotstudio-->
    <PosLimit refjoint="Joint2" min="-155" max="80" />
    <PosLimit refjoint="Joint3" min="-75" max="160" />
    <PosLimit refjoint="Joint4" min="-180" max="180" />
    <PosLimit refjoint="Joint5" min="-140" max="140" />
    <PosLimit refjoint="Joint6" min="-360" max="360" />

    <VelLimit refjoint="Joint1" max="190" />
    <VelLimit refjoint="Joint2" max="1750" />
    <VelLimit refjoint="Joint3" max="200" /> 
    <VelLimit refjoint="Joint4" max="400" />
    <VelLimit refjoint="Joint5" max="360" />
    <VelLimit refjoint="Joint6" max="610" />

    <!--<AccLimit refjoint="Joint1" max="120" />
    <AccLimit refjoint="Joint2" max="120" />
    <AccLimit refjoint="Joint3" max="120" /> 
    <AccLimit refjoint="Joint4" max="120" />
    <AccLimit refjoint="Joint5" max="120" />
    <AccLimit refjoint="Joint6" max="120" />-->

    <Drawable name="BaseGeo" refframe="Robot_Base">
        <RPY> 0 0 0 </RPY> <Pos> 0 0 0</Pos>
        <Polytope file="../RobotData/Inovance/IRS300_20/Geometry/base" unit="MM" color="255 255 255"/></Drawable>
    <Drawable name="J1Geo" refframe="Joint1">
        <RPY> 0 0 0 </RPY> <Pos> 0 0 -500 </Pos>
        <Polytope file="../RobotData/Inovance/IRS300_20/Geometry/joint1" unit="MM" color="255 255 255"/></Drawable>
    <Drawable name="J2Geo" refframe="Joint2">
        <RPY> -90 0 -90 </RPY> <Pos> -500 170 0 </Pos>
        <Polytope file="../RobotData/Inovance/IRS300_20/Geometry/joint2" unit="MM" color="255 255 255"/></Drawable>    
    <Drawable name="J3Geo" refframe="Joint3">
        <RPY> -90 0 -90 </RPY> <Pos> -1280 170 0</Pos>
        <Polytope file="../RobotData/Inovance/IRS300_20/Geometry/joint3" unit="MM" color="255 255 255"/></Drawable>  
    <Drawable name="J4Geo" refframe="Joint4">
        <RPY> 0 -90 180 </RPY> <Pos> -1420 0 -930 </Pos>
        <Polytope file="../RobotData/Inovance/IRS300_20/Geometry/joint4" unit="MM" color="255 255 255"/></Drawable>
    <Drawable name="J5Geo" refframe="Joint5">
        <RPY> -90 0 -90 </RPY> <Pos> -1420 930 0</Pos>  
        <Polytope file="../RobotData/Inovance/IRS300_20/Geometry/joint5" unit="MM" color="255 255 255"/></Drawable>
    <Drawable name="J6Geo" refframe="Joint6">
        <RPY> 0 -90 180 </RPY> <Pos> -1420 0 -930 </Pos>  
        <Polytope file="../RobotData/Inovance/IRS300_20/Geometry/joint6" unit="MM" color="169 169 169"/></Drawable>

    <CollisionSetup file="../RobotData/Inovance/IRS300_20/CollisionSetup.xml" />

    <!--Q name="Home">0 0 -1.5707963  0 0 0</Q-->
    <Q name="Home">0 0 0 0 0 0</Q>

</SerialDevice>
